ai_essay_evaluator/__init__.py
ai_essay_evaluator/__main__.py
ai_essay_evaluator/cli.py
ai_essay_evaluator/py.typed
ai_essay_evaluator/evaluator/__init__.py
ai_essay_evaluator/evaluator/async_logger.py
ai_essay_evaluator/evaluator/cli.py
ai_essay_evaluator/evaluator/cost_analysis.py
ai_essay_evaluator/evaluator/file_handler.py
ai_essay_evaluator/evaluator/openai_client.py
ai_essay_evaluator/evaluator/processor.py
ai_essay_evaluator/evaluator/utils.py
ai_essay_evaluator/trainer/__init__.py
ai_essay_evaluator/trainer/cli.py
ai_essay_evaluator/trainer/finetuner.py
ai_essay_evaluator/trainer/generator.py
ai_essay_evaluator/trainer/merge.py
ai_essay_evaluator/trainer/uploader.py
ai_essay_evaluator/trainer/validator.py
ai_essay_evaluator-1.3.2.dist-info/licenses/LICENSE
ai_essay_evaluator-1.3.2.dist-info/METADATA
ai_essay_evaluator-1.3.2.dist-info/WHEEL
ai_essay_evaluator-1.3.2.dist-info/top_level.txt
ai_essay_evaluator-1.3.2.dist-info/RECORD
