Metadata-Version: 2.4
Name: ai-essay-evaluator
Version: 1.3.2
Summary: This repository provides a modular framework for generating, validating, merging, uploading, and fine-tuning OpenAI GPT-4o-mini models using structured JSONL datasets.
Author-email: Mark Moreno <mamoreno@aldineisd.org>
License: MIT
Project-URL: Bug Tracker, https://github.com/markm-io/ai-essay-evaluator/issues
Project-URL: Changelog, https://github.com/markm-io/ai-essay-evaluator/blob/main/CHANGELOG.md
Project-URL: documentation, https://ai-essay-evaluator.readthedocs.io
Project-URL: repository, https://github.com/markm-io/ai-essay-evaluator
Classifier: Development Status :: 2 - Pre-Alpha
Classifier: Intended Audience :: Developers
Classifier: Natural Language :: English
Classifier: Operating System :: OS Independent
Classifier: Programming Language :: Python :: 3.10
Classifier: Programming Language :: Python :: 3.11
Classifier: Programming Language :: Python :: 3.12
Classifier: Programming Language :: Python :: 3.13
Classifier: Topic :: Software Development :: Libraries
Requires-Python: >=3.10
License-File: LICENSE
Requires-Dist: ftfy>=6.3.1
Requires-Dist: openai>=1.65.3
Requires-Dist: pandas>=2.2.3
Requires-Dist: pandas-stubs==2.3.2.250926
Requires-Dist: pydantic>=2.10.6
Requires-Dist: tenacity>=9.0.0
Requires-Dist: typer>=0.15.2
Dynamic: license-file
